r_sdk/__init__.py
r_sdk/client.py
r_sdk/exceptions.py
r_sdk/types.py
r_cli_sdk-0.1.0.dist-info/METADATA
r_cli_sdk-0.1.0.dist-info/WHEEL
r_cli_sdk-0.1.0.dist-info/RECORD
