Metadata-Version: 2.4
Name: r-cli-sdk
Version: 0.1.0
Summary: Python SDK for R CLI - Local AI Agent Runtime
Project-URL: Homepage, https://github.com/raym33/r
Project-URL: Documentation, https://github.com/raym33/r/tree/main/sdks/python
Project-URL: Repository, https://github.com/raym33/r
Author: R CLI Team
License-Expression: MIT
Keywords: agent,ai,llm,local,sdk
Classifier: Development Status :: 4 - Beta
Classifier: Intended Audience :: Developers
Classifier: License :: OSI Approved :: MIT License
Classifier: Programming Language :: Python :: 3
Classifier: Programming Language :: Python :: 3.10
Classifier: Programming Language :: Python :: 3.11
Classifier: Programming Language :: Python :: 3.12
Classifier: Programming Language :: Python :: 3.13
Classifier: Topic :: Software Development :: Libraries :: Python Modules
Requires-Python: >=3.10
Requires-Dist: httpx>=0.25.0
Provides-Extra: dev
Requires-Dist: pytest-asyncio>=0.21; extra == 'dev'
Requires-Dist: pytest>=7.0; extra == 'dev'
Requires-Dist: ruff>=0.1; extra == 'dev'
